{
  "paper_type": "cream",
  "page_count": 346,
  "trim_size_inches": {
    "width": 5.83,
    "height": 8.27
  },
  "bleed_inches": 0.125,
  "spine_width_inches": 0.865,
  "total_cover_inches": {
    "width": 12.775,
    "height": 8.52
  },
  "dpi": 300,
  "total_cover_pixels": {
    "width": 3832,
    "height": 2556
  },
  "source_front": "manuscript/cover/cover_front.png",
  "source_back": "manuscript/cover/cover_back.png",
  "output_wrap": "output/cover/kdp_wrap_a5_cream_346p_300dpi.png",
  "output_flattened_pdf": "output/cover/kdp_wrap_a5_cream_346p_300dpi_flattened.pdf"
}